rhg_compute_tools/__init__.py
rhg_compute_tools/cli.py
rhg_compute_tools/gcs.py
rhg_compute_tools/kubernetes.py
rhg_compute_tools/utils.py
rhg_compute_tools/xarray.py
rhg_compute_tools/design/__init__.py
rhg_compute_tools/design/colors.py
rhg_compute_tools/design/plotting.py
rhg_compute_tools/design/styles/rhg_note.mplstyle
rhg_compute_tools/design/styles/rhg_powerpoint.mplstyle
rhg_compute_tools/design/styles/rhg_powerpoint_wide.mplstyle
rhg_compute_tools/io_tools/__init__.py
rhg_compute_tools/io_tools/readers.py
rhg_compute_tools/io_tools/writers.py
rhg_compute_tools-1.3.3.dist-info/LICENSE
rhg_compute_tools-1.3.3.dist-info/METADATA
rhg_compute_tools-1.3.3.dist-info/WHEEL
rhg_compute_tools-1.3.3.dist-info/entry_points.txt
rhg_compute_tools-1.3.3.dist-info/top_level.txt
rhg_compute_tools-1.3.3.dist-info/RECORD
