Metadata-Version: 2.1
Name: rhg-compute-tools
Version: 1.3.3
Summary: Tools for using compute.rhg.com and compute.impactlab.org
Home-page: https://github.com/RhodiumGroup/rhg_compute_tools
Author: Michael Delgado
Author-email: mdelgado@rhg.com
License: MIT license
Keywords: rhg_compute_tools
Platform: UNKNOWN
Classifier: Development Status :: 4 - Beta
Classifier: Intended Audience :: Science/Research
Classifier: License :: OSI Approved :: MIT License
Classifier: Natural Language :: English
Classifier: Programming Language :: Python :: 3
Classifier: Programming Language :: Python :: 3.7
Classifier: Programming Language :: Python :: 3.8
Requires-Dist: google-cloud-storage
Requires-Dist: click
Requires-Dist: dask-gateway
Requires-Dist: pandas
Requires-Dist: xarray
Requires-Dist: matplotlib
Requires-Dist: numpy
Requires-Dist: bottleneck
Requires-Dist: importlib-metadata; python_version < "3.8"
